AUTHORS
LICENSE
MANIFEST.in
README.rst
requirements.txt
setup.cfg
setup.py
babel/babel.bat
babel/babel.cfg
babel/babel.sh
babel/mmw.pot
mongo_mail_web/__init__.py
mongo_mail_web/admin.py
mongo_mail_web/constants.py
mongo_mail_web/countries.py
mongo_mail_web/extensions.py
mongo_mail_web/flask_utils.py
mongo_mail_web/form_helpers.py
mongo_mail_web/forms.py
mongo_mail_web/geoip_tools.py
mongo_mail_web/graphite_attime.py
mongo_mail_web/manager.py
mongo_mail_web/metric_utils.py
mongo_mail_web/metrics.py
mongo_mail_web/models.py
mongo_mail_web/settings.py
mongo_mail_web/tasks.py
mongo_mail_web/utils.py
mongo_mail_web/wsgi.py
mongo_mail_web.egg-info/PKG-INFO
mongo_mail_web.egg-info/SOURCES.txt
mongo_mail_web.egg-info/dependency_links.txt
mongo_mail_web.egg-info/entry_points.txt
mongo_mail_web.egg-info/not-zip-safe
mongo_mail_web.egg-info/pbr.json
mongo_mail_web.egg-info/requires.txt
mongo_mail_web.egg-info/top_level.txt
mongo_mail_web/static/mmw/login.css
mongo_mail_web/static/mmw/flags/flags.css
mongo_mail_web/static/mmw/flags/flags16.png
mongo_mail_web/static/mmw/htmltable_export/demo.php
mongo_mail_web/static/mmw/htmltable_export/html2canvas.js
mongo_mail_web/static/mmw/htmltable_export/jquery.base64.js
mongo_mail_web/static/mmw/htmltable_export/simple_html_dom.php
mongo_mail_web/static/mmw/htmltable_export/tableExport.js
mongo_mail_web/static/mmw/htmltable_export/tableExtractor.php
mongo_mail_web/static/mmw/htmltable_export/icons/Thumbs.db
mongo_mail_web/static/mmw/htmltable_export/icons/csv.png
mongo_mail_web/static/mmw/htmltable_export/icons/json.png
mongo_mail_web/static/mmw/htmltable_export/icons/pdf.png
mongo_mail_web/static/mmw/htmltable_export/icons/png.png
mongo_mail_web/static/mmw/htmltable_export/icons/ppt.png
mongo_mail_web/static/mmw/htmltable_export/icons/sql.png
mongo_mail_web/static/mmw/htmltable_export/icons/txt.png
mongo_mail_web/static/mmw/htmltable_export/icons/word.png
mongo_mail_web/static/mmw/htmltable_export/icons/xls.png
mongo_mail_web/static/mmw/htmltable_export/icons/xml.png
mongo_mail_web/static/mmw/htmltable_export/jspdf/jspdf.js
mongo_mail_web/static/mmw/htmltable_export/jspdf/libs/base64.js
mongo_mail_web/static/mmw/htmltable_export/jspdf/libs/sprintf.js
mongo_mail_web/static/mmw/js/dashboard/counters.js
