Metadata-Version: 1.1
Name: mongo-mail-web
Version: 0.1.1
Summary: Web UI for Mongo Mail Server
Home-page: https://github.com/srault95/mongo-mail-web
Author: Stéphane RAULT
Author-email: stephane.rault@radicalspam.org
License: BSD
Platform: UNKNOWN
Classifier: Development Status :: 4 - Beta
Classifier: License :: OSI Approved :: BSD License
Classifier: Operating System :: POSIX :: Linux
Classifier: Programming Language :: Python
Classifier: Programming Language :: Python :: 2
Classifier: Programming Language :: Python :: 2.7
Classifier: Framework :: Flask
Classifier: Environment :: Web Environment
Classifier: Intended Audience :: Developers
Classifier: Intended Audience :: System Administrators
Classifier: Topic :: Communications :: Email
Classifier: Topic :: Communications :: Email :: Filters
Classifier: Natural Language :: English
Classifier: Natural Language :: French
